{
  "code": "KA-03",
  "region": "Kasturi Nagar",
  "city": "Bengaluru",
  "state": "Karnataka",
  "stateCode": "KA",
  "district": "Bengaluru Urban",
  "division": "Bengaluru Urban Division",
  "description": "The KA-03 Regional Transport Office (Kasturi Nagar RTO) handles vehicle registrations and transport services for this region in Bengaluru Urban district.",
  "established": "N/A",
  "address": "CA-15, N.G.E.F, East, Kasturi Nagar, Bengaluru (East)",
  "pinCode": "560043",
  "phone": "080-29735190",
  "email": "rtobnge-ka@nic.in",
  "jurisdictionAreas": [
    "Agaram",
    "Appareddy Palya",
    "Ashoknagar",
    "Austin Town",
    "Bangalore East Railway Station",
    "Byappanahalli",
    "Challaghatta",
    "Chikkabanasawadi",
    "Church Road",
    "Cleveland Town",
    "Coles Park",
    "Commercial Street",
    "Cooks Town",
    "Cox Town",
    "Dickenson Road",
    "Doddakunte",
    "Dommalur Extension",
    "Dukanahalli",
    "Elagondana Palya",
    "Frazer Town",
    "Gandhi Statue",
    "Gouthampura",
    "Grass Farm",
    "Hainess Road",
    "Indiranagar",
    "Jeevan Bheema Nagar",
    "Jeevanahalli",
    "Jogupalyam",
    "Kadram Palya",
    "Kallenahalli",
    "Kammanahalli",
    "Kodihalli",
    "Lingamangala",
    "Lingarajapura",
    "Machali Betta",
    "Madavaraya Mudaliyar Road",
    "Maruthi Sevanagar",
    "Murphy Town",
    "Nagannanapalya",
    "Neelasandra",
    "Parade Grounds",
    "Pillamma Garden Extension",
    "Richards Town",
    "Richmond Town",
    "Sevanagar",
    "Someswarapura",
    "St. Johns Town",
    "Subbayyapalya",
    "Thippasandra",
    "Trinity Circle",
    "Ukada Palya",
    "Ulsoor",
    "Vannarpet",
    "Veerapilly Street",
    "Viveknagar"
  ]
}
